<?xml version="1.0" encoding="utf-8"?>

<resources>
    <color name="holo_green_light">#ff110000</color>
    <color name="holo_green_dark">#ff110000</color> <!--QS background-->
    <color name="holo_red_light">#ff110000</color> <!--notification_panel_solid_background-->
    <color name="holo_red_dark">#ff110000</color> <!--notification_guts_bg_color, notification_shade_bg_color -->
    <color name="holo_orange_light">#cc110000</color> <!--notification_material_background_dimmed_color-->
    <color name="holo_orange_dark">#ff110000</color> <!--notification_material_background_low_priority_color-->

    <color name="notification_action_list">#ff424242</color> <!--notification reply box-->
    <color name="notification_primary_text_color_light">#ffffffff</color>
    <color name="notification_secondary_text_color_light">#ffc1c1c1</color>
</resources>